vhs/__init__.py
vhs/__main__.py
vhs/_version.py
vhs/py.typed
vhs-1.1.1.dist-info/licenses/LICENSE
vhs-1.1.1.dist-info/METADATA
vhs-1.1.1.dist-info/WHEEL
vhs-1.1.1.dist-info/top_level.txt
vhs-1.1.1.dist-info/RECORD
