Metadata-Version: 2.4
Name: vhs
Version: 1.1.1
Summary: Write terminal GIFs as code for integration testing and demoing your CLI tools, now with python
Author-email: Tamika Nomara <taminomara@gmail.com>
License-Expression: MIT
Project-URL: Documentation, https://python-vhs.readthedocs.io/en/stable/
Project-URL: Issues, https://github.com/taminomara/python-vhs/issues/
Project-URL: Source, https://github.com/taminomara/python-vhs/
Project-URL: Changelog, https://github.com/taminomara/python-vhs/blob/main/CHANGELOG.md
Classifier: Development Status :: 5 - Production/Stable
Classifier: Programming Language :: Python :: 3
Classifier: Programming Language :: Python :: 3 :: Only
Classifier: Programming Language :: Python :: 3.11
Classifier: Programming Language :: Python :: 3.12
Classifier: Programming Language :: Python :: 3.13
Classifier: Topic :: Software Development :: Libraries :: Python Modules
Classifier: Intended Audience :: Developers
Classifier: Typing :: Typed
Requires-Python: >=3.11
License-File: LICENSE
Requires-Dist: PyGithub<2.9,>=1.59
Requires-Dist: requests<2.33,>=2.31
Dynamic: license-file
